stemplate/__init__.py
stemplate/__main__.py
stemplate/_version.py
stemplate/default.conf
stemplate/core/__init__.py
stemplate/core/colors.py
stemplate/core/files.py
stemplate/main/__init__.py
stemplate/main/date.py
stemplate/main/head.py
stemplate-1.0.1.dist-info/LICENSE.txt
stemplate-1.0.1.dist-info/METADATA
stemplate-1.0.1.dist-info/WHEEL
stemplate-1.0.1.dist-info/entry_points.txt
stemplate-1.0.1.dist-info/top_level.txt
stemplate-1.0.1.dist-info/RECORD
