Metadata-Version: 2.1
Name: stemplate
Version: 1.0.1
Summary: A short description of the package.
Author-email: Author Name <author@email.adress>
Project-URL: Homepage, https://gitlab.com/stemplate/pypack
Project-URL: Bug Tracker, https://gitlab.com/stemplate/pypack/issues
Project-URL: Documentation, https://stemplate.gitlab.io/pypack
Classifier: Programming Language :: Python :: 3
Classifier: License :: OSI Approved :: GNU General Public License v3 (GPLv3)
Classifier: Topic :: Software Development
Classifier: Intended Audience :: Developers
Requires-Python: >=3.9
License-File: LICENSE.txt
Requires-Dist: numpy (==1.24.2)
